devpi_pr/__init__.py
devpi_pr/client.py
devpi_pr/server.py
devpi_pr/views.py
devpi_pr-1.0.0.dist-info/LICENSE
devpi_pr-1.0.0.dist-info/METADATA
devpi_pr-1.0.0.dist-info/WHEEL
devpi_pr-1.0.0.dist-info/entry_points.txt
devpi_pr-1.0.0.dist-info/top_level.txt
devpi_pr-1.0.0.dist-info/RECORD
