Metadata-Version: 2.1
Name: devpi-pr
Version: 1.0.0
Summary: devpi-pr: a pull request workflow plugin for devpi-server and devpi-client
Home-page: http://doc.devpi.net
License: MIT
Platform: UNKNOWN
Classifier: Development Status :: 5 - Production/Stable
Classifier: Environment :: Web Environment
Classifier: Intended Audience :: Developers
Classifier: Intended Audience :: System Administrators
Classifier: License :: OSI Approved :: MIT License
Classifier: Programming Language :: Python
Classifier: Topic :: Internet :: WWW/HTTP
Classifier: Topic :: Internet :: WWW/HTTP :: WSGI :: Application
Classifier: Programming Language :: Python :: Implementation :: PyPy
Classifier: Programming Language :: Python :: 3.5
Classifier: Programming Language :: Python :: 3.6
Classifier: Programming Language :: Python :: 3.7
Requires-Python: >=3.5
Requires-Dist: appdirs
Requires-Dist: attrs
Provides-Extra: client
Requires-Dist: devpi-client (>=4.3.0) ; extra == 'client'
Provides-Extra: dev
Requires-Dist: pytest ; extra == 'dev'
Requires-Dist: pytest-cov ; extra == 'dev'
Requires-Dist: pytest-flake8 ; extra == 'dev'
Requires-Dist: webtest ; extra == 'dev'
Provides-Extra: server
Requires-Dist: devpi-server (>=5.0.0) ; extra == 'server'
